Sequence Detector/design.sv
// Code your design here
module bitcheck(
  input wire inp,
  input wire clk,
  output reg [1:0] state,
  output reg out
);
  parameter S0=2'b00,S1=2'b01,S2=2'b10,S3=2'b11;
  always @(negedge clk)
    begin
      case({state,inp})
         3'b000:begin state<=S1; out<=0; end
         3'b001:begin state<=S0; out<=0; end
         3'b010:begin state<=S1; out<=0; end
         3'b011:begin state<=S2; out<=0; end
         3'b100:begin state<=S3; out<=1; end
         3'b101:begin state<=S0; out<=0; end
         3'b110:begin state<=S1; out<=0; end
         3'b111:begin state<=S2; out<=0; end
        default:begin state<=S0; out<=0; end
      endcase
    end
endmodule

Sequence Detector/testbench.sv
// Code your testbench here
// or browse Examples
module test;
  reg clk,inp;
  wire out;
  wire [1:0] state;
  
  bitcheck uut(
    .clk(clk),
    .inp(inp),
    .out(out),
    .state(state)
  );
  
  always
    #5 clk=~clk;
  initial
    begin
      $dumpfile("bitcheck.vcd");
      $dumpvars(1,test);
                
      clk=0;
      $monitor($time,"inp=%b,out=%b,state=%b",inp,out,state);
      #5 inp=1;
      #10 inp=0;
    #10  inp=1;
      #10 inp=1;
    #10  inp=0;
      #10 inp=1;
     #10 inp=0;
     #10 inp=1;
    #10  inp=0;
      #5 $finish;
    end
  endmodule

Sequence Detector/bitcheck.vcd
$date
	Sun Jul 19 10:21:38 2026
$end
$version
	Icarus Verilog
$end
$timescale
	1s
$end
$scope module test $end
$var wire 2 ! state [1:0] $end
$var wire 1 " out $end
$var reg 1 # clk $end
$var reg 1 $ inp $end
$upscope $end
$enddefinitions $end
$comment Show the parameter values. $end
$dumpall
$end
#0
$dumpvars
x$
0#
0"
b0 !
$end
#5
1$
1#
#10
0#
#15
1#
0$
#20
b1 !
0#
#25
1#
1$
#30
b10 !
0#
#35
1#
#40
b0 !
0#
#45
1#
0$
#50
b1 !
0#
#55
1#
1$
#60
b10 !
0#
#65
1#
0$
#70
1"
b11 !
0#
#75
1#
1$
#80
0"
b10 !
0#
#85
1#
0$
#90
1"
b11 !
0#
